dagster_datahub/__init__.py
dagster_datahub/py.typed
dagster_datahub/resources.py
dagster_datahub/version.py
dagster_datahub-1.0.5.dist-info/LICENSE
dagster_datahub-1.0.5.dist-info/METADATA
dagster_datahub-1.0.5.dist-info/WHEEL
dagster_datahub-1.0.5.dist-info/top_level.txt
dagster_datahub-1.0.5.dist-info/RECORD
